[
    {
        "name": "GM Server",
        "description": "A framework for interfacing between Java game servers and GameMaker clients",
        "language": [
            "Java"
        ],
        "repo": "https://github.com/f0rbit/gm-server",
        "link": null,
        "icon": "gm_server.png",
        "status": "live",
        "hidden": false
    },
    {
        "name": "Dark Dungeon",
        "description": "Custom coded Minecraft Server",
        "language": [
            "Java"
        ],
        "repo": "https://github.com/TheDarkTurnip/dark-dungeon/tree/plugin/plugins/source%20code/dark-dungeon-multi",
        "link": null,
        "icon": "dark_dungeon.png",
        "status": "development",
        "hidden": false
    },
    {
        "name": "Bit Quest",
        "description": "A small MMORPG made in GameMaker & Java",
        "language": [
            "Java",
            "GML"
        ],
        "repo": null,
        "link": null,
        "icon": "bit_quest.png",
        "status": "development",
        "hidden": false
    },
    {
        "name": "/forbit.dev",
        "description": "Website for myself",
        "language": [
            "JavaScript",
            "React",
            "HTML"
        ],
        "repo": "https://github.com/f0rbit/forbit-dev",
        "link": null,
        "icon": "forbit_dev.png",
        "status": "live",
        "hidden": false
    },
    {
        "name": "Arena",
        "description": "A multiplayer fast-paced 1v1 capture the flag game",
        "language": [
            "Java",
            "GML"
        ],
        "link": null,
        "status": "development",
        "icon": null,
        "hidden": false
    },
    {
        "name": "Rich Frog",
        "description": "Game designed for increasing mouse accuracy and speed for gamers",
        "language": [
            "GML"
        ],
        "repo": "https://github.com/f0rbit/rich-frog",
        "link": {
            "url": "https://f0rbit.itch.io/rich-frog",
            "text": "Play"
        },
        "icon": null,
        "status": "live",
        "hidden": false
    },
    {
        "name": "Pixel Fly",
        "description": "A peaceful game for passing time",
        "language": [
            "GML"
        ],
        "repo": "https://github.com/f0rbit/pixel-fly",
        "link": null,
        "icon": null,
        "status": "stopped",
        "hidden": true
    },
    {
        "name": "LOL Terminal",
        "description": "A League of Legends match history client built for the linux terminal",
        "language": [
            "C++"
        ],
        "repo": "https://github.com/f0rbit/match-history-terminal",
        "link": null,
        "icon": null,
        "status": "released",
        "hidden": false
    },
    {
        "name": "Algorithm Dungeon",
        "description": "A visual demonstration of different types of algorithms used to generate dungeons for games.",
        "language": [
            "GML"
        ],
        "repo": null,
        "link": null,
        "icon": null,
        "status": "development",
        "hidden": true
    },
    {
        "name": "Planning",
        "description": "A user interface for planning & managing school work. Made for my Year 12 IT class.",
        "language": [
            "VisualBasic",
            ".NET"
        ],
        "repo": null,
        "link": null,
        "icon": null,
        "status": "abandoned",
        "hidden": false
    },
    {
        "name": "Ryan Can't Jump",
        "description": "A platforming game where you would have to replay all the levels backwards once finished, but without the ability to jump.",
        "language": [
            "GML"
        ],
        "repo": null,
        "link": null,
        "icon": null,
        "status": "abandoned",
        "hidden": true
    },
    {
        "name": "Clumsy Santa",
        "description": "A game made for the Extra Credits 2019 Christmas Game Jam.",
        "language": [
            "GML"
        ],
        "repo": null,
        "link": {
            "url": "https://f0rbit.itch.io/clumsy-santa",
            "text": "Play"
        },
        "icon": null,
        "status": "live",
        "hidden": false
    }
]